{
  "totalCapital": 75.3,
  "wildCapital": 75.3,
  "joakoCapital": 0,
  "wildEquity": 75.3,
  "joakoEquity": 0,
  "pnlCycle": -43.97,
  "pnlPercent": -36.87,
  "openPositions": 0,
  "timestamp": "2026-05-06T19:00:35.463069",
  "btc": {
    "price": 81025.1,
    "change": 0.0
  },
  "positions": [],
  "lastTrades": [],
  "watchCoins": [
    {
      "symbol": "0GUSDT",
      "price": 0.5522,
      "change": 0.0,
      "signal": "\u2014"
    },
    {
      "symbol": "1000000BABYDOGEUSDT",
      "price": 0.0004362,
      "change": 0.0,
      "signal": "\u2014"
    },
    {
      "symbol": "1000000MOGUSDT",
      "price": 0.15471,
      "change": 0.0,
      "signal": "\u2014"
    },
    {
      "symbol": "1000BONKUSDT",
      "price": 0.0067,
      "change": 0.0,
      "signal": "\u2014"
    },
    {
      "symbol": "1000FLOKIUSDT",
      "price": 0.03312,
      "change": 0.0,
      "signal": "\u2014"
    },
    {
      "symbol": "1000LUNCUSDT",
      "price": 0.08866,
      "change": 0.0,
      "signal": "\u2014"
    },
    {
      "symbol": "1000NEIROCTOUSDT",
      "price": 0.09635,
      "change": 0.0,
      "signal": "\u2014"
    },
    {
      "symbol": "1000PEPEUSDT",
      "price": 0.004107,
      "change": 0.0,
      "signal": "\u2014"
    },
    {
      "symbol": "1000TAGUSDT",
      "price": 1.499,
      "change": 0.0,
      "signal": "\u2014"
    },
    {
      "symbol": "1000TURBOUSDT",
      "price": 1.2842,
      "change": 0.0,
      "signal": "\u2014"
    }
  ],
  "capitalHistory": [
    {
      "date": "28/04",
      "capital": 119.27
    },
    {
      "date": "29/04",
      "capital": 61.53
    },
    {
      "date": "30/04",
      "capital": 59.98
    },
    {
      "date": "01/05",
      "capital": 59.31
    },
    {
      "date": "02/05",
      "capital": 58.54
    },
    {
      "date": "03/05",
      "capital": 59.04
    },
    {
      "date": "04/05",
      "capital": 55.98
    },
    {
      "date": "05/05",
      "capital": 58.89
    },
    {
      "date": "06/05",
      "capital": 75.3
    }
  ]
}