{
  "totalCapital": 55.27,
  "wildCapital": 55.27,
  "joakoCapital": 0,
  "wildEquity": 55.27,
  "joakoEquity": 0,
  "pnlCycle": -64.0,
  "pnlPercent": -53.66,
  "openPositions": 0,
  "timestamp": "2026-05-12T08:00:53.035001",
  "btc": {
    "price": 80466.7,
    "change": 0.0
  },
  "positions": [],
  "lastTrades": [],
  "watchCoins": [
    {
      "symbol": "0GUSDT",
      "price": 0.5526,
      "change": 0.0,
      "signal": "\u2014"
    },
    {
      "symbol": "1000000MOGUSDT",
      "price": 0.16397,
      "change": 0.0,
      "signal": "\u2014"
    },
    {
      "symbol": "1000BONKUSDT",
      "price": 0.007097,
      "change": 0.0,
      "signal": "\u2014"
    },
    {
      "symbol": "1000FLOKIUSDT",
      "price": 0.0355,
      "change": 0.0,
      "signal": "\u2014"
    },
    {
      "symbol": "1000LUNCUSDT",
      "price": 0.09843,
      "change": 0.0,
      "signal": "\u2014"
    },
    {
      "symbol": "1000NEIROCTOUSDT",
      "price": 0.09749,
      "change": 0.0,
      "signal": "\u2014"
    },
    {
      "symbol": "1000PEPEUSDT",
      "price": 0.004144,
      "change": 0.0,
      "signal": "\u2014"
    },
    {
      "symbol": "1000TAGUSDT",
      "price": 1.344,
      "change": 0.0,
      "signal": "\u2014"
    },
    {
      "symbol": "1000TURBOUSDT",
      "price": 1.2652,
      "change": 0.0,
      "signal": "\u2014"
    },
    {
      "symbol": "1000XECUSDT",
      "price": 0.008264,
      "change": 0.0,
      "signal": "\u2014"
    }
  ],
  "capitalHistory": [
    {
      "date": "28/04",
      "capital": 119.27
    },
    {
      "date": "29/04",
      "capital": 61.53
    },
    {
      "date": "30/04",
      "capital": 59.98
    },
    {
      "date": "01/05",
      "capital": 59.31
    },
    {
      "date": "02/05",
      "capital": 58.54
    },
    {
      "date": "03/05",
      "capital": 59.04
    },
    {
      "date": "04/05",
      "capital": 55.98
    },
    {
      "date": "05/05",
      "capital": 58.89
    },
    {
      "date": "06/05",
      "capital": 75.3
    },
    {
      "date": "07/05",
      "capital": 73.74
    },
    {
      "date": "08/05",
      "capital": 73.74
    },
    {
      "date": "10/05",
      "capital": 73.16
    },
    {
      "date": "11/05",
      "capital": 53.9
    },
    {
      "date": "12/05",
      "capital": 55.27
    }
  ]
}